sqlvector/__init__.py
sqlvector/config.py
sqlvector/embedding.py
sqlvector/exceptions.py
sqlvector/loader.py
sqlvector/logger.py
sqlvector/models.py
sqlvector/protocols.py
sqlvector/query.py
sqlvector/backends/__init__.py
sqlvector/backends/duckdb/__init__.py
sqlvector/backends/duckdb/config.py
sqlvector/backends/duckdb/loader.py
sqlvector/backends/duckdb/models.py
sqlvector/backends/duckdb/querier.py
sqlvector/backends/duckdb/rag.py
sqlvector/backends/postgres/__init__.py
sqlvector/backends/postgres/config.py
sqlvector/backends/postgres/event_loop_utils.py
sqlvector/backends/postgres/loader.py
sqlvector/backends/postgres/models.py
sqlvector/backends/postgres/querier.py
sqlvector/backends/postgres/rag.py
sqlvector/backends/sqlite/__init__.py
sqlvector/backends/sqlite/config.py
sqlvector/backends/sqlite/loader.py
sqlvector/backends/sqlite/models.py
sqlvector/backends/sqlite/querier.py
sqlvector/backends/sqlite/rag.py
sqlvector-0.2.0.dist-info/licenses/LICENSE
sqlvector-0.2.0.dist-info/METADATA
sqlvector-0.2.0.dist-info/WHEEL
sqlvector-0.2.0.dist-info/top_level.txt
sqlvector-0.2.0.dist-info/RECORD
