Metadata-Version: 2.4
Name: sqlvector
Version: 0.2.0
Summary: A flexible RAG library using SQL databases as vector stores through SQLAlchemy
Author-email: Paul Bergeron <paul.d.bergeron@gmail.com>
License: MIT
Project-URL: Repository, https://github.com/dinedal/sql-rag
Project-URL: Issues, https://github.com/dinedal/sql-rag/issues
Project-URL: Documentation, https://github.com/dinedal/sql-rag/wiki
Project-URL: Changelog, https://github.com/dinedal/sql-rag/blob/main/CHANGELOG.md
Keywords: rag,vector-search,sqlalchemy,duckdb,sqlite,embeddings,retrieval-augmented-generation
Classifier: Development Status :: 3 - Alpha
Classifier: Intended Audience :: Developers
Classifier: License :: OSI Approved :: MIT License
Classifier: Programming Language :: Python :: 3
Classifier: Programming Language :: Python :: 3.12
Classifier: Topic :: Database
Classifier: Topic :: Scientific/Engineering :: Artificial Intelligence
Classifier: Topic :: Software Development :: Libraries :: Python Modules
Classifier: Operating System :: OS Independent
Requires-Python: >=3.12
License-File: LICENSE
Requires-Dist: asyncpg>=0.30.0
Requires-Dist: build>=1.2.2.post1
Requires-Dist: sqlalchemy[asyncio]>=2.0.41
Requires-Dist: sqlite-vss>=0.1.2
Requires-Dist: tqdm>=4.67.1
Provides-Extra: test
Requires-Dist: pytest>=8.0.0; extra == "test"
Requires-Dist: pytest-asyncio>=0.23.0; extra == "test"
Requires-Dist: aiosqlite>=0.19.0; extra == "test"
Requires-Dist: sqlite-vss>=0.1.2; extra == "test"
Provides-Extra: duckdb
Requires-Dist: duckdb>=1.3.0; extra == "duckdb"
Requires-Dist: polars>=1.15.0; extra == "duckdb"
Requires-Dist: numpy>=1.21.0; extra == "duckdb"
Requires-Dist: pyarrow>=10.0.0; extra == "duckdb"
Requires-Dist: duckdb-engine>=0.17.0; extra == "duckdb"
Provides-Extra: postgres
Requires-Dist: psycopg2-binary>=2.9.0; extra == "postgres"
Requires-Dist: pgvector>=0.3.0; extra == "postgres"
Dynamic: license-file
